[{    
    "id":"4096",    
    "text":"高三"   
},{    
    "id":"2048",    
    "text":"高二"   
},{    
    "id":"1024",    
    "text":"高一"   
},{    
    "id":"512",    
    "text":"初三"   
},{    
    "id":"256",    
    "text":"初二"   
},{    
    "id":"128",    
    "text":"初一"   
},{    
    "id":"64",    
    "text":"小六"   
},{    
    "id":"32",    
    "text":"小五"   
},{    
    "id":"16",    
    "text":"小四"   
},{    
    "id":"8",    
    "text":"小三"   
},{    
    "id":"4",    
    "text":"小二"   
},{    
    "id":"2",    
    "text":"小一"   
},{    
    "id":"1",    
    "text":"幼儿"   
}] 